pyjon.utils-0.7-py2.7-nspkg.pth
pyjon.utils-0.7.dist-info/DESCRIPTION.rst
pyjon.utils-0.7.dist-info/top_level.txt
pyjon.utils-0.7.dist-info/METADATA
pyjon.utils-0.7.dist-info/RECORD
pyjon.utils-0.7.dist-info/WHEEL
pyjon.utils-0.7.dist-info/metadata.json
pyjon.utils-0.7.dist-info/namespace_packages.txt
pyjon.utils-0.7.dist-info/entry_points.txt
pyjon/utils/main.py
pyjon/utils/__init__.py
pyjon/utils/base_converter.py
