Metadata-Version: 1.1
Name: pyjon.utils
Version: 0.7
Summary: Useful tools library with classes to do singletons, dynamic function pointers...
Home-page: UNKNOWN
Author: Florent Aide
Author-email: florent.aide@gmail.com
License: MIT
Platform: UNKNOWN
Classifier: Programming Language :: Python
Classifier: Topic :: Software Development :: Libraries :: Python Modules
